exssh/__init__.py
exssh/__main__.py
exssh/core.py
exssh-0.1.1.dist-info/METADATA
exssh-0.1.1.dist-info/WHEEL
exssh-0.1.1.dist-info/entry_points.txt
exssh-0.1.1.dist-info/licenses/LICENSE
exssh-0.1.1.dist-info/RECORD
