Metadata-Version: 2.4
Name: exssh
Version: 0.1.1
Summary: Provide automation capability for any ssh client.
Project-URL: homepage, https://github.com/darkclip/exssh
Project-URL: repository, https://github.com/darkclip/exssh
Project-URL: documentation, https://github.com/darkclip/exssh
Author-email: darkclip <darkclip@hanv.dev>
License-Expression: MIT
License-File: LICENSE
Keywords: automation,expect,mosh,ssh,zssh
Requires-Python: >=3.8
Requires-Dist: pexpect>=4.9.0
Provides-Extra: bitwarden
Requires-Dist: exbw>=0.1.0; extra == 'bitwarden'
